{
    "version": 5,
    "channels": [
        {
            "name": "CCTV-1 综合",
            "webUrl": "https://tv.cctv.com/live/cctv1/",
            "rule": "cctv",
            "cover":"https://piccpndks.v.kcdnvip.com/pic/cctv1_2.png"
        },
        {
            "name": "CCTV-2 财经",
            "webUrl": "https://tv.cctv.com/live/cctv2/",
            "rule": "ysp",
            "cover":"https://piccpndks.v.kcdnvip.com/pic/cctv2_2.png"
        },
        {
            "name": "CCTV-3 综艺",
            "webUrl": "https://tv.cctv.com/live/cctv3/",
            "rule": "cctv",
            "cover":"https://piccpndks.v.kcdnvip.com/pic/cctv3_2.png"
        },
        {
            "name": "CCTV-4 中文国际（亚）",
            "webUrl": "https://tv.cctv.com/live/cctv4/",
            "rule": "cctv",
            "cover":"https://piccpndks.v.kcdnvip.com/pic/cctv4_2.png"
        },
        {
            "name": "CCTV 4 中文国际 (欧)",
            "webUrl": "https://tv.cctv.com/live/cctveurope/index.shtml",
            "rule": "cctv"
        },
        {
            "name": "CCTV 4 中文国际 (美)",
            "webUrl": "https://tv.cctv.com/live/cctvamerica/",
            "rule": "cctv"
        },
        {
            "name": "CCTV-5 体育",
            "webUrl": "https://www.yangshipin.cn/tv/home?pid=600001818",
            "rule": "ysp"
        },
        {
            "name": "CCTV-5+ 体育赛事",
            "webUrl": "https://www.yangshipin.cn/tv/home?pid=600001817",
            "rule": "ysp",
            "cover":"https://piccpndks.v.kcdnvip.com/pic/cctv5plus_2.png"
        },
        {
            "name": "CCTV-6 电影",
            "webUrl": "https://www.yangshipin.cn/tv/home?pid=600108442",
            "rule": "ysp"
        },
        {
            "name": "CCTV-7 国防军事",
            "webUrl": "https://www.yangshipin.cn/tv/home?pid=600004092",
            "rule": "ysp"
        },
        {
            "name": "CCTV-8 电视剧",
            "webUrl": "https://www.yangshipin.cn/tv/home?pid=600001803",
            "rule": "ysp"
        },
        {
            "name": "CCTV-9 纪录",
            "webUrl": "https://www.yangshipin.cn/tv/home?pid=600004078",
            "rule": "ysp"
        },
        {
            "name": "CCTV-10 科教",
            "webUrl": "https://www.yangshipin.cn/tv/home?pid=600001805",
            "rule": "ysp"
        },
        {
            "name": "CCTV-11 戏曲",
            "webUrl": "https://www.yangshipin.cn/tv/home?pid=600001806",
            "rule": "ysp"
        },
        {
            "name": "CCTV-12 社会与法",
            "webUrl": "https://www.yangshipin.cn/tv/home?pid=600001807",
            "rule": "ysp"
        },
        {
            "name": "CCTV-13 新闻",
            "webUrl": "https://www.yangshipin.cn/tv/home?pid=600001811",
            "rule": "ysp"
        },
        {
            "name": "CCTV-14 少儿",
            "webUrl": "https://www.yangshipin.cn/tv/home?pid=600001809",
            "rule": "ysp"
        },
        {
            "name": "CCTV-15 音乐",
            "webUrl": "https://www.yangshipin.cn/tv/home?pid=600001815",
            "rule": "ysp"
        },
        {
            "name": "CCTV-16 奥林匹克",
            "webUrl": "https://www.yangshipin.cn/tv/home?pid=600098637",
            "rule": "ysp"
        },
        {
            "name": "CCTV-17 农业农村",
            "webUrl": "https://www.yangshipin.cn/tv/home?pid=600001810",
            "rule": "ysp"
        },
        {
            "name": "CCTV 4K",
            "webUrl": "https://www.yangshipin.cn/tv/home?pid=600002264",
            "rule": "ysp"
        },
        {
            "name": "CCTV 风云剧场",
            "webUrl": "https://www.yangshipin.cn/tv/home?pid=600099658",
            "rule": "ysp"
        },
        {
            "name": "CCTV 第一剧场",
            "webUrl": "https://www.yangshipin.cn/tv/home?pid=600099655",
            "rule": "ysp"
        },
        {
            "name": "CCTV 怀旧剧场",
            "webUrl": "https://www.yangshipin.cn/tv/home?pid=600099620",
            "rule": "ysp"
        },
        {
            "name": "CGTN",
            "webUrl": "https://www.yangshipin.cn/tv/home?pid=600014550",
            "rule": "ysp"
        },
        {
            "name": "CGTN 纪录频道",
            "webUrl": "https://www.yangshipin.cn/tv/home?pid=600084781",
            "rule": "ysp"
        },
        {
            "name": "北京卫视",
            "webUrl": "https://www.yangshipin.cn/tv/home?pid=600002309",
            "rule": "ysp"
        },
        {
            "name": "江苏卫视",
            "webUrl": "https://www.yangshipin.cn/tv/home?pid=600002521",
            "rule": "ysp"
        },
        {
            "name": "东方卫视",
            "webUrl": "https://www.yangshipin.cn/tv/home?pid=600002483",
            "rule": "ysp"
        },
        {
            "name": "浙江卫视",
            "webUrl": "https://www.yangshipin.cn/tv/home?pid=600002520",
            "rule": "ysp"
        },
        {
            "name": "湖南卫视",
            "webUrl": "https://www.yangshipin.cn/tv/home?pid=600002475",
            "rule": "ysp"
        },
        {
            "name": "湖北卫视",
            "webUrl": "https://www.yangshipin.cn/tv/home?pid=600002508",
            "rule": "ysp"
        },
        {
            "name": "广东卫视",
            "webUrl": "https://www.yangshipin.cn/tv/home?pid=600002485",
            "rule": "ysp"
        },
        {
            "name": "广西卫视",
            "webUrl": "https://www.yangshipin.cn/tv/home?pid=600002509",
            "rule": "ysp"
        },
        {
            "name": "黑龙江卫视",
            "webUrl": "https://www.yangshipin.cn/tv/home?pid=600002498",
            "rule": "ysp"
        },
        {
            "name": "海南卫视",
            "webUrl": "https://www.yangshipin.cn/tv/home?pid=600002506",
            "rule": "ysp"
        },
        {
            "name": "重庆卫视",
            "webUrl": "https://www.yangshipin.cn/tv/home?pid=600002531",
            "rule": "ysp"
        },
        {
            "name": "深圳卫视",
            "webUrl": "https://www.yangshipin.cn/tv/home?pid=600002481",
            "rule": "ysp"
        },
        {
            "name": "四川卫视",
            "webUrl": "https://www.yangshipin.cn/tv/home?pid=600002516",
            "rule": "ysp"
        },
        {
            "name": "河南卫视",
            "webUrl": "https://www.yangshipin.cn/tv/home?pid=600002525",
            "rule": "ysp"
        },
        {
            "name": "福建东南卫视",
            "webUrl": "https://www.yangshipin.cn/tv/home?pid=600002484",
            "rule": "ysp"
        },
        {
            "name": "贵州卫视",
            "webUrl": "https://www.yangshipin.cn/tv/home?pid=600002490",
            "rule": "ysp"
        },
        {
            "name": "江西卫视",
            "webUrl": "https://www.yangshipin.cn/tv/home?pid=600002503",
            "rule": "ysp"
        },
        {
            "name": "辽宁卫视",
            "webUrl": "https://www.yangshipin.cn/tv/home?pid=600002505",
            "rule": "ysp"
        },
        {
            "name": "安徽卫视",
            "webUrl": "https://www.yangshipin.cn/tv/home?pid=600002532",
            "rule": "ysp"
        },
        {
            "name": "河北卫视",
            "webUrl": "https://www.yangshipin.cn/tv/home?pid=600002493",
            "rule": "ysp"
        },
        {
            "name": "山东卫视",
            "webUrl": "https://www.yangshipin.cn/tv/home?pid=600002513",
            "rule": "ysp"
        }
    ],
    "ruleUrlMap": {
        "ysp": "https://api.7na7.com/myApi/liveTV/ysp.min.js",
        "cctv": "https://api.7na7.com/myApi/liveTV/cctv.min.js"
    }
}